sipwhitelist/__init__.py
sipwhitelist/sipwhitelist.py
sipwhitelist-0.2.2.dist-info/LICENSE
sipwhitelist-0.2.2.dist-info/METADATA
sipwhitelist-0.2.2.dist-info/WHEEL
sipwhitelist-0.2.2.dist-info/top_level.txt
sipwhitelist-0.2.2.dist-info/RECORD
