Metadata-Version: 2.1
Name: sipwhitelist
Version: 0.2.2
Summary: Library that interacts with SIP to build an indicator whitelist system.
Home-page: https://github.com/ace-ecosystem/sipwhitelist
Author: Matthew Wilson
Author-email: automationator@runbox.com
License: Apache 2.0
Keywords: sipwhitelist
Platform: UNKNOWN
Classifier: Development Status :: 3 - Alpha
Classifier: Intended Audience :: Developers
Classifier: Topic :: Software Development :: Build Tools
Classifier: License :: OSI Approved :: Apache Software License
Classifier: Programming Language :: Python :: 3
Classifier: Programming Language :: Python :: 3.3
Classifier: Programming Language :: Python :: 3.4
Classifier: Programming Language :: Python :: 3.5
Requires-Dist: urlfinderlib
